nmcli/__init__.py
nmcli/_connection.py
nmcli/_const.py
nmcli/_device.py
nmcli/_exception.py
nmcli/_general.py
nmcli/_helper.py
nmcli/_networking.py
nmcli/_radio.py
nmcli/_system.py
nmcli/py.typed
nmcli/data/__init__.py
nmcli/data/connection.py
nmcli/data/device.py
nmcli/data/general.py
nmcli/data/hotspot.py
nmcli/data/radio.py
nmcli/dummy/__init__.py
nmcli/dummy/_connection.py
nmcli/dummy/_device.py
nmcli/dummy/_general.py
nmcli/dummy/_networking.py
nmcli/dummy/_radio.py
nmcli-1.6.0.dist-info/licenses/LICENSE.txt
nmcli-1.6.0.dist-info/METADATA
nmcli-1.6.0.dist-info/WHEEL
nmcli-1.6.0.dist-info/top_level.txt
nmcli-1.6.0.dist-info/RECORD
