Metadata-Version: 2.4
Name: nmcli
Version: 1.6.0
Summary: A python wrapper library for the network-manager cli client
Author: ushiboy
License-Expression: MIT
Project-URL: Homepage, https://github.com/ushiboy/nmcli
Classifier: Programming Language :: Python :: 3
Classifier: Operating System :: POSIX :: Linux
Requires-Python: >=3.7
License-File: LICENSE.txt
Dynamic: license-file
